pyfortiztp/__init__.py
pyfortiztp/core/__init__.py
pyfortiztp/core/api.py
pyfortiztp/core/fortiztp.py
pyfortiztp/models/__init__.py
pyfortiztp/models/devices.py
pyfortiztp-1.0.1.dist-info/LICENSE
pyfortiztp-1.0.1.dist-info/METADATA
pyfortiztp-1.0.1.dist-info/WHEEL
pyfortiztp-1.0.1.dist-info/top_level.txt
pyfortiztp-1.0.1.dist-info/RECORD
